README.md
setup.py
limitpages/__init__.py
limitpages/apps.py
limitpages/models.py
limitpages.egg-info/PKG-INFO
limitpages.egg-info/SOURCES.txt
limitpages.egg-info/dependency_links.txt
limitpages.egg-info/top_level.txt
limitpages/migrations/0001_initial.py
limitpages/migrations/__init__.py